civis_jupyter_ext/__init__.py
civis_jupyter_ext/magics/__init__.py
civis_jupyter_ext/magics/query.py
civis_jupyter_ext/static/index.js
civis_jupyter_extensions-1.2.0.dist-info/LICENSE.txt
civis_jupyter_extensions-1.2.0.dist-info/METADATA
civis_jupyter_extensions-1.2.0.dist-info/WHEEL
civis_jupyter_extensions-1.2.0.dist-info/top_level.txt
civis_jupyter_extensions-1.2.0.dist-info/RECORD
