Metadata-Version: 2.1
Name: civis-jupyter-extensions
Version: 1.2.0
Summary: Tools for using Civis Platform with Jupyter notebooks
Author-email: Civis Analytics <opensource@civisanalytics.com>
License: BSD-3-Clause
Project-URL: Homepage, https://www.civisanalytics.com
Project-URL: Source, https://github.com/civisanalytics/civis-jupyter-extensions
Classifier: Development Status :: 5 - Production/Stable
Classifier: License :: OSI Approved :: BSD License
Classifier: Programming Language :: Python
Classifier: Programming Language :: Python :: 3
Classifier: Programming Language :: Python :: 3 :: Only
Requires-Python: >=3.9
License-File: LICENSE.txt
Requires-Dist: civis
Requires-Dist: ipython >=5.4
Requires-Dist: pandas
Provides-Extra: dev
Requires-Dist: bandit ; extra == 'dev'
Requires-Dist: black ==24.4.2 ; extra == 'dev'
Requires-Dist: build ==1.2.1 ; extra == 'dev'
Requires-Dist: flake8 ==7.0.0 ; extra == 'dev'
Requires-Dist: pip-audit ; extra == 'dev'
Requires-Dist: pytest ==8.2.2 ; extra == 'dev'
Requires-Dist: twine ==5.1.0 ; extra == 'dev'
